flx/__init__.py
flx/flx.py
flx/util.py
the_flx-0.1.2.dist-info/LICENSE
the_flx-0.1.2.dist-info/METADATA
the_flx-0.1.2.dist-info/WHEEL
the_flx-0.1.2.dist-info/top_level.txt
the_flx-0.1.2.dist-info/RECORD
