Metadata-Version: 2.1
Name: the-flx
Version: 0.1.2
Summary: Rewrite emacs-flx in Python
Home-page: https://github.com/the-flx/flx.py
Author: Jen-Chieh Shen
Author-email: jcs090218@gmail.com
License: MIT
Project-URL: Source Code, https://github.com/the-flx/flx.py
Requires-Python: >=3.9
License-File: LICENSE
